autoslug/__init__.py
autoslug/__main__.py
autoslug/__version__.py
autoslug/autoslug.py
autoslug/cli.py
autoslug/config/__init__.py
autoslug/config/arguments.py
autoslug/config/defaults.py
autoslug/utils/__init__.py
autoslug/utils/filesystem.py
autoslug/utils/logging.py
autoslug/utils/parser.py
autoslug-1.0.5.dist-info/METADATA
autoslug-1.0.5.dist-info/WHEEL
autoslug-1.0.5.dist-info/entry_points.txt
autoslug-1.0.5.dist-info/licenses/LICENSE.txt
autoslug-1.0.5.dist-info/RECORD
